pdbstruct/__init__.py
pdbstruct/asa.py
pdbstruct/bgrid.py
pdbstruct/cli.py
pdbstruct/hollow.defaults.txt
pdbstruct/hollow.py
pdbstruct/parse.py
pdbstruct/soup.py
pdbstruct/spacehash.py
pdbstruct/store.py
pdbstruct/util.py
pdbstruct/vector3d.py
pdbstruct/volume.py
pdbstruct-0.3.dist-info/METADATA
pdbstruct-0.3.dist-info/WHEEL
pdbstruct-0.3.dist-info/entry_points.txt
pdbstruct-0.3.dist-info/RECORD
