Metadata-Version: 2.4
Name: pdbstruct
Version: 0.3
Summary: Tools for analyzing protein structures
Project-URL: Homepage, https://github.com/boscoh/pdbstruct
License-Expression: MIT
Classifier: Operating System :: OS Independent
Classifier: Programming Language :: Python :: 3
Requires-Python: >=3.12
Requires-Dist: bitarray>=3.4.2
Requires-Dist: click>=8.2.1
Requires-Dist: hatchling>=1.27.0
Requires-Dist: nose2>=0.15.1
Requires-Dist: tqdm>=4.67.1
